{"crest4_databases":
    {
        "midori253darn": {
            "title": "Midori v253",
            "url": "https://crest4.s3-eu-west-1.amazonaws.com/midori253darn.tar.gz"
        },
        "silvamod128": {
            "title": "SilvaMod v128",
            "url": "https://crest4.s3-eu-west-1.amazonaws.com/silvamod128.tar.gz"
        },
        "mitofish": {
            "title": "MitoFish",
            "url": "https://crest4.s3-eu-west-1.amazonaws.com/mitofish.tar.gz"
        },
        "silvamod138pr2": {
            "title": "SilvaMod v138 PR2",
            "url": "https://crest4.s3-eu-west-1.amazonaws.com/silvamod138pr2.tar.gz"
        },
        "ssuome": {
            "title": "ssuome v1.1",
            "url": "https://crest4.s3-eu-west-1.amazonaws.com/ssuome.tar.gz"
        }
    }
}